pych9329/__init__.py
pych9329/chip_command.py
pych9329/exceptions.py
pych9329/frame_utils.py
pych9329/hid_code_map.py
pych9329/hid_code_table.py
pych9329/keyboard.py
pych9329/mouse.py
pych9329/py.typed
pych9329/struct_utils.py
pych9329-0.1.6.dist-info/LICENSE
pych9329-0.1.6.dist-info/METADATA
pych9329-0.1.6.dist-info/WHEEL
pych9329-0.1.6.dist-info/RECORD
