Metadata-Version: 2.3
Name: pych9329
Version: 0.1.6
Summary: Python module to control the ch9329
License: MIT
Author: wevsty
Author-email: ty@wevs.org
Requires-Python: >3.10
Classifier: License :: OSI Approved :: MIT License
Classifier: Programming Language :: Python :: 3
Classifier: Programming Language :: Python :: 3.11
Classifier: Programming Language :: Python :: 3.12
Classifier: Programming Language :: Python :: 3.13
Requires-Dist: pyserial (>=3.5,<4.0)
Project-URL: Repository, https://github.com/wevsty/pych9329
